.gitignore
setup.py
edp/__init__.py
edp/cli.py
edp/composite/__init__.py
edp/composite/parser/ana_rcp.py
edp/composite/parser/csv.py
edp/composite/parser/exp.py
edp/composite/parser/rawlen.py
edp/composite/parser/sample.py
edp/composite/parser/txt.py
edp_cli.egg-info/PKG-INFO
edp_cli.egg-info/SOURCES.txt
edp_cli.egg-info/dependency_links.txt
edp_cli.egg-info/entry_points.txt
edp_cli.egg-info/requires.txt
edp_cli.egg-info/top_level.txt