Metadata-Version: 1.1
Name: edp-cli
Version: 0.2.0
Summary: A platform for the ingestion and management of experimental data.
Home-page: https://github.com/OpenChemistry/edp
Author: Kitware Inc
Author-email: UNKNOWN
License: BSD 3-Clause
Platform: UNKNOWN
Classifier: Development Status :: 3 - Alpha
Classifier: License :: OSI Approved :: BSD License
Classifier: Programming Language :: Python :: 3
